LICENSE
MANIFEST.in
README.rst
mrglog.py
mrglog_demo.py
setup.py
mrglog.egg-info/PKG-INFO
mrglog.egg-info/SOURCES.txt
mrglog.egg-info/dependency_links.txt
mrglog.egg-info/top_level.txt