Metadata-Version: 1.1
Name: mrglog
Version: 0.1.1
Summary: MRG log module
Home-page: https://github.com/ltrilety/mrglog
Author: Luboš Tříletý
Author-email: ltrilety@redhat.com
License: Apache 2.0
Platform: UNKNOWN
Classifier: Intended Audience :: Developers
Classifier: Topic :: Software Development :: Testing
Classifier: Topic :: System :: Logging
Classifier: Programming Language :: Python :: 2
Classifier: Programming Language :: Python :: 2.7
Classifier: Programming Language :: Python :: 3
Classifier: Programming Language :: Python :: 3.5
